{
  "items": [
    {
      "title_ru": "Кольцо на Рождество",
      "title_en": "A Ring for Christmas",
      "year": 2020,
      "kinopoisk_id": 1238268,
      "type": "movie",
      "iframe_url": "",
      "added_date": "2021-01-07 02:12:02",
      "block": false,
      "translator": "многоголосый закадровый",
      "translator_id": 89,
      "quality": "HDTV"
    },
    {
      "title_ru": "Олег",
      "title_en": "Oleg",
      "year": 2019,
      "kinopoisk_id": 1112591,
      "type": "movie",
      "iframe_url": "",
      "added_date": "2021-01-07 02:11:01",
      "block": false,
      "translator": "многоголосый закадровый",
      "translator_id": 89,
      "quality": "WEB-DL"
    },
    {
      "title_ru": "РобоЛеди",
      "title_en": "RoboWoman",
      "year": 2019,
      "kinopoisk_id": 1126477,
      "type": "movie",
      "iframe_url": "",
      "added_date": "2021-01-07 02:09:01",
      "block": false,
      "translator": "многоголосый закадровый",
      "translator_id": 89,
      "quality": "WEB-DL"
    },
    {
      "title_ru": "Зелёная кошка",
      "title_en": "Pisica Verde",
      "year": 2020,
      "kinopoisk_id": 10382436,
      "type": "movie",
      "iframe_url": "",
      "added_date": "2021-01-07 02:08:01",
      "block": false,
      "translator": "многоголосый закадровый",
      "translator_id": 89,
      "quality": "WEB-DL"
    },
    {
      "title_ru": "Комната",
      "title_en": "La stanza",
      "year": 2021,
      "kinopoisk_id": 1440552,
      "type": "movie",
      "iframe_url": "",
      "added_date": "2021-01-07 02:06:01",
      "block": false,
      "translator": "многоголосый закадровый",
      "translator_id": 89,
      "quality": "WEB-DL"
    },
    {
      "title_ru": "Джед",
      "title_en": "JED",
      "year": 2019,
      "kinopoisk_id": 1133053,
      "type": "movie",
      "iframe_url": "",
      "added_date": "2021-01-07 02:04:01",
      "block": false,
      "translator": "многоголосый закадровый",
      "translator_id": 89,
      "quality": "WEB-DL"
    },
    {
      "title_ru": "Сериал закрывают!",
      "title_en": "A Christmas Cancellation / Cancellation",
      "year": 2020,
      "kinopoisk_id": 1349215,
      "type": "movie",
      "iframe_url": "",
      "added_date": "2021-01-07 02:02:01",
      "block": false,
      "translator": "многоголосый закадровый",
      "translator_id": 89,
      "quality": "WEB-DL"
    },
    {
      "title_ru": "Sous le même toit",
      "title_en": "",
      "year": 2017,
      "kinopoisk_id": 1000242,
      "type": "movie",
      "iframe_url": "",
      "added_date": "2021-01-06 21:46:02",
      "block": false,
      "translator": "Профессиональный (многоголосый)",
      "translator_id": 126,
      "quality": "BDRip"
    },
    {
      "title_ru": "Рождество с Джой",
      "title_en": "Christmas Joy",
      "year": 2018,
      "kinopoisk_id": 1164268,
      "type": "movie",
      "iframe_url": "",
      "added_date": "2021-01-06 20:56:02",
      "block": false,
      "translator": "Профессиональный (многоголосый)",
      "translator_id": 126,
      "quality": "SATRip"
    },
    {
      "title_ru": "Лена и белый тигр",
      "title_en": "Lena and Snowball",
      "year": 2021,
      "kinopoisk_id": 1236682,
      "type": "movie",
      "iframe_url": "",
      "added_date": "2021-01-06 19:17:01",
      "block": false,
      "translator": "многоголосый закадровый",
      "translator_id": 89,
      "quality": "WEB-DL"
    },
    {
      "title_ru": "Нина из леса",
      "title_en": "Nina of the Woods",
      "year": 2019,
      "kinopoisk_id": 1097908,
      "type": "movie",
      "iframe_url": "",
      "added_date": "2021-01-06 19:13:02",
      "block": false,
      "translator": "многоголосый закадровый",
      "translator_id": 89,
      "quality": "WEB-DL"
    },
    {
      "title_ru": "Наследие Хоуп",
      "title_en": "Hope's Legacy",
      "year": 2020,
      "kinopoisk_id": 1273901,
      "type": "movie",
      "iframe_url": "",
      "added_date": "2021-01-06 19:11:02",
      "block": false,
      "translator": "многоголосый закадровый",
      "translator_id": 89,
      "quality": "WEB-DL"
    },
    {
      "title_ru": "Ножовка",
      "title_en": "Hacksaw /  The Followers",
      "year": 2020,
      "kinopoisk_id": 1147238,
      "type": "movie",
      "iframe_url": "",
      "added_date": "2021-01-06 19:10:01",
      "block": false,
      "translator": "многоголосый закадровый",
      "translator_id": 89,
      "quality": "WEB-DL"
    },
    {
      "title_ru": "Потоп",
      "title_en": "The Flood",
      "year": 2020,
      "kinopoisk_id": 1341280,
      "type": "movie",
      "iframe_url": "",
      "added_date": "2021-01-06 19:08:01",
      "block": false,
      "translator": "многоголосый закадровый",
      "translator_id": 89,
      "quality": "WEB-DL"
    },
    {
      "title_ru": "Все ждут Рождества 2: Люси и магический кристалл",
      "title_en": "Julemandens datter 2",
      "year": 2020,
      "kinopoisk_id": 1292938,
      "type": "movie",
      "iframe_url": "",
      "added_date": "2021-01-06 19:06:01",
      "block": false,
      "translator": "Дубляж [Чистый звук]",
      "translator_id": 109,
      "quality": "WEB-DL"
    },
    {
      "title_ru": "Американская мечта",
      "title_en": "American Dream",
      "year": 2021,
      "kinopoisk_id": 602963,
      "type": "movie",
      "iframe_url": "",
      "added_date": "2021-01-06 19:05:02",
      "block": false,
      "translator": "многоголосый закадровый",
      "translator_id": 89,
      "quality": "WEB-DL"
    },
    {
      "title_ru": "Алгоритм: Блаженство",
      "title_en": "Algorithm: Bliss",
      "year": 2021,
      "kinopoisk_id": 800776,
      "type": "movie",
      "iframe_url": "",
      "added_date": "2021-01-06 19:04:01",
      "block": false,
      "translator": "многоголосый закадровый",
      "translator_id": 89,
      "quality": "WEB-DL"
    },
    {
      "title_ru": "Камень в воде",
      "title_en": "A Stone in the Water",
      "year": 2019,
      "kinopoisk_id": 1355306,
      "type": "movie",
      "iframe_url": "",
      "added_date": "2021-01-06 19:02:02",
      "block": false,
      "translator": "многоголосый закадровый",
      "translator_id": 89,
      "quality": "WEB-DL"
    },
    {
      "title_ru": "Агата и полуночные убийства",
      "title_en": "Agatha and the Midnight Murders",
      "year": 2020,
      "kinopoisk_id": 1318978,
      "type": "movie",
      "iframe_url": "",
      "added_date": "2021-01-06 10:36:01",
      "block": false,
      "translator": "Дубляж",
      "translator_id": 82,
      "quality": "BDRip"
    },
    {
      "title_ru": "Агата и проклятие Иштар",
      "title_en": "Agatha and the Curse of Ishtar",
      "year": 2019,
      "kinopoisk_id": 1311450,
      "type": "movie",
      "iframe_url": "",
      "added_date": "2021-01-06 10:35:02",
      "block": false,
      "translator": "Дубляж",
      "translator_id": 82,
      "quality": "BDRip"
    }
  ]
}
