{
  "items": [
    {
      "title_ru": "Всё или ничего",
      "title_en": "The Longest Yard",
      "year": 2005,
      "kinopoisk_id": 77577,
      "type": "movie",
      "iframe_url": "",
      "added_date": "2018-07-27 13:29:20",
      "block": false,
      "translator": "Дубляж",
      "translator_id": 82,
      "quality": "HDRip"
    },
    {
      "title_ru": "Дом восковых фигур",
      "title_en": "House of Wax",
      "year": 2005,
      "kinopoisk_id": 64212,
      "type": "movie",
      "iframe_url": "",
      "added_date": "2018-07-27 13:29:20",
      "block": false,
      "translator": "Дубляж",
      "translator_id": 82,
      "quality": "HDRip"
    },
    {
      "title_ru": "Цыплёнок Цыпа",
      "title_en": "Chicken Little",
      "year": 2005,
      "kinopoisk_id": 70953,
      "type": "movie",
      "iframe_url": "",
      "added_date": "2018-07-27 13:29:11",
      "block": false,
      "translator": "Дубляж",
      "translator_id": 82,
      "quality": "HDRip"
    },
    {
      "title_ru": "Доказательство",
      "title_en": "Proof",
      "year": 2004,
      "kinopoisk_id": 47055,
      "type": "movie",
      "iframe_url": "",
      "added_date": "2018-07-27 13:29:11",
      "block": false,
      "translator": "Дубляж",
      "translator_id": 82,
      "quality": "HDRip"
    },
    {
      "title_ru": "Сломанные цветы",
      "title_en": "Broken Flowers",
      "year": 2005,
      "kinopoisk_id": 81581,
      "type": "movie",
      "iframe_url": "",
      "added_date": "2018-07-27 13:29:11",
      "block": false,
      "translator": "Дубляж",
      "translator_id": 82,
      "quality": "HDRip"
    },
    {
      "title_ru": "Комик",
      "title_en": "The Comedian",
      "year": 2016,
      "kinopoisk_id": 596212,
      "type": "movie",
      "iframe_url": "",
      "added_date": "2018-07-27 13:29:11",
      "block": false,
      "translator": "многоголосый закадровый",
      "translator_id": 89,
      "quality": "WEB-DL"
    },
    {
      "title_ru": "Иллюзия полета",
      "title_en": "Flightplan",
      "year": 2005,
      "kinopoisk_id": 81873,
      "type": "movie",
      "iframe_url": "",
      "added_date": "2018-07-27 13:29:11",
      "block": false,
      "translator": "Дубляж",
      "translator_id": 82,
      "quality": "HDRip"
    },
    {
      "title_ru": "Космос между нами",
      "title_en": "The Space Between Us",
      "year": 2017,
      "kinopoisk_id": 924990,
      "type": "movie",
      "iframe_url": "",
      "added_date": "2018-07-27 13:29:11",
      "block": false,
      "translator": "Дубляж",
      "translator_id": 82,
      "quality": "WEB-DL"
    },
    {
      "title_ru": "Призрак в доспехах",
      "title_en": "Ghost in the Shell",
      "year": 2017,
      "kinopoisk_id": 843789,
      "type": "movie",
      "iframe_url": "",
      "added_date": "2018-07-27 13:29:11",
      "block": false,
      "translator": "Дубляж",
      "translator_id": 82,
      "quality": "WEB-DL"
    },
    {
      "title_ru": "Шесть демонов Эмили Роуз",
      "title_en": "The Exorcism of Emily Rose",
      "year": 2005,
      "kinopoisk_id": 84967,
      "type": "movie",
      "iframe_url": "",
      "added_date": "2018-07-27 13:27:58",
      "block": false,
      "translator": "Дубляж",
      "translator_id": 82,
      "quality": "HDRip"
    },
    {
      "title_ru": "Эон Флакс",
      "title_en": "Æon Flux",
      "year": 2005,
      "kinopoisk_id": 77426,
      "type": "movie",
      "iframe_url": "",
      "added_date": "2018-07-27 13:27:58",
      "block": false,
      "translator": "Дубляж",
      "translator_id": 82,
      "quality": "HDRip"
    },
    {
      "title_ru": "Подальше от тебя",
      "title_en": "In Her Shoes",
      "year": 2005,
      "kinopoisk_id": 77463,
      "type": "movie",
      "iframe_url": "",
      "added_date": "2018-07-27 13:27:58",
      "block": false,
      "translator": "Дубляж",
      "translator_id": 82,
      "quality": "HDRip"
    },
    {
      "title_ru": "Кинг Конг",
      "title_en": "King Kong",
      "year": 2005,
      "kinopoisk_id": 5908,
      "type": "movie",
      "iframe_url": "",
      "added_date": "2018-07-27 13:27:58",
      "block": false,
      "translator": "Дубляж",
      "translator_id": 82,
      "quality": "HDRip"
    },
    {
      "title_ru": "Элизабеттаун",
      "title_en": "Elizabethtown",
      "year": 2005,
      "kinopoisk_id": 61238,
      "type": "movie",
      "iframe_url": "",
      "added_date": "2018-07-27 13:27:58",
      "block": false,
      "translator": "Дубляж",
      "translator_id": 82,
      "quality": "HDRip"
    },
    {
      "title_ru": "Мой лучший любовник",
      "title_en": "Prime",
      "year": 2005,
      "kinopoisk_id": 77180,
      "type": "movie",
      "iframe_url": "",
      "added_date": "2018-07-27 13:27:58",
      "block": false,
      "translator": "Дубляж",
      "translator_id": 82,
      "quality": "BDRip"
    },
    {
      "title_ru": "Между небом и землей",
      "title_en": "Just Like Heaven",
      "year": 2005,
      "kinopoisk_id": 85182,
      "type": "movie",
      "iframe_url": "",
      "added_date": "2018-07-27 13:27:58",
      "block": false,
      "translator": "Дубляж",
      "translator_id": 82,
      "quality": "HDRip"
    },
    {
      "title_ru": "Уоллес и Громит: Проклятие кролика-оборотня",
      "title_en": "The Curse of the Were-Rabbit",
      "year": 2005,
      "kinopoisk_id": 22399,
      "type": "movie",
      "iframe_url": "",
      "added_date": "2018-07-27 13:27:58",
      "block": false,
      "translator": "Дубляж",
      "translator_id": 82,
      "quality": "WEBRip"
    },
    {
      "title_ru": "Оправданная жестокость",
      "title_en": "A History of Violence",
      "year": 2005,
      "kinopoisk_id": 78320,
      "type": "movie",
      "iframe_url": "",
      "added_date": "2018-07-27 10:09:11",
      "block": false,
      "translator": "Дубляж",
      "translator_id": 82,
      "quality": "HDRip"
    },
    {
      "title_ru": "И грянул гром",
      "title_en": "A Sound of Thunder",
      "year": 2004,
      "kinopoisk_id": 4473,
      "type": "movie",
      "iframe_url": "",
      "added_date": "2018-07-27 10:09:11",
      "block": false,
      "translator": "Дубляж",
      "translator_id": 82,
      "quality": "HDRip"
    },
    {
      "title_ru": "Пиджак",
      "title_en": "The Jacket",
      "year": 2004,
      "kinopoisk_id": 47382,
      "type": "movie",
      "iframe_url": "",
      "added_date": "2018-07-27 10:09:10",
      "block": false,
      "translator": "Дубляж",
      "translator_id": 82,
      "quality": "HDRip"
    }
  ]
}
