{
  "items": [
    {
      "title_ru": "Петсон и Финдус. Финдус переезжает",
      "title_en": "Pettersson und Findus - Findus zieht um",
      "year": 2018,
      "kinopoisk_id": 1022844,
      "type": "movie",
      "iframe_url": "",
      "added_date": "2019-04-17 11:03:13",
      "block": false,
      "translator": "многоголосый закадровый",
      "translator_id": 89,
      "quality": "BDRip"
    },
    {
      "title_ru": "Усыновление",
      "title_en": "Pupille",
      "year": 2018,
      "kinopoisk_id": 1092091,
      "type": "movie",
      "iframe_url": "",
      "added_date": "2019-04-17 01:47:16",
      "block": false,
      "translator": "многоголосый закадровый",
      "translator_id": 89,
      "quality": "WEB-DL"
    },
    {
      "title_ru": "Анжелика",
      "title_en": "Angelica",
      "year": 2015,
      "kinopoisk_id": 741640,
      "type": "movie",
      "iframe_url": "",
      "added_date": "2019-04-17 01:44:15",
      "block": false,
      "translator": "многоголосый закадровый",
      "translator_id": 89,
      "quality": "WEB-DL"
    },
    {
      "title_ru": "Смотри мою любовь",
      "title_en": "",
      "year": 2018,
      "kinopoisk_id": 1167854,
      "type": "movie",
      "iframe_url": "",
      "added_date": "2019-04-17 00:06:33",
      "block": [
        "RU"
      ],
      "translator": "Не требуется",
      "translator_id": 92,
      "quality": "TS"
    },
    {
      "title_ru": "Ветер перемен",
      "title_en": "Le vent tourne",
      "year": 2018,
      "kinopoisk_id": 1070477,
      "type": "movie",
      "iframe_url": "",
      "added_date": "2019-04-16 22:57:10",
      "block": false,
      "translator": "многоголосый закадровый",
      "translator_id": 89,
      "quality": "WEB-DL"
    },
    {
      "title_ru": "Жена",
      "title_en": "The Wife",
      "year": 2017,
      "kinopoisk_id": 891414,
      "type": "movie",
      "iframe_url": "",
      "added_date": "2019-04-16 22:50:37",
      "block": false,
      "translator": "Дубляж",
      "translator_id": 82,
      "quality": "BDRemux"
    },
    {
      "title_ru": "Круг",
      "title_en": "Colo",
      "year": 2017,
      "kinopoisk_id": 963224,
      "type": "movie",
      "iframe_url": "",
      "added_date": "2019-04-16 22:18:56",
      "block": false,
      "translator": "многоголосый закадровый",
      "translator_id": 89,
      "quality": "WEB-DL"
    },
    {
      "title_ru": "Не доверяй никому",
      "title_en": "Trust No 1",
      "year": 2019,
      "kinopoisk_id": 1094895,
      "type": "movie",
      "iframe_url": "",
      "added_date": "2019-04-16 22:15:42",
      "block": false,
      "translator": "многоголосый закадровый",
      "translator_id": 89,
      "quality": "WEB-DLRip"
    },
    {
      "title_ru": "Бамблби",
      "title_en": "Bumblebee",
      "year": 2018,
      "kinopoisk_id": 952241,
      "type": "movie",
      "iframe_url": "",
      "added_date": "2019-04-16 13:50:36",
      "block": false,
      "translator": "Дубляж [Лицензия]",
      "translator_id": 107,
      "quality": "4К"
    },
    {
      "title_ru": "Затерянные во льдах",
      "title_en": "Arctic",
      "year": 2018,
      "kinopoisk_id": 1069265,
      "type": "movie",
      "iframe_url": "",
      "added_date": "2019-04-16 13:08:49",
      "block": false,
      "translator": "многоголосый закадровый",
      "translator_id": 89,
      "quality": "HDTV"
    },
    {
      "title_ru": "Встреча одноклассников",
      "title_en": "Klassentreffen",
      "year": 2018,
      "kinopoisk_id": 1063617,
      "type": "movie",
      "iframe_url": "",
      "added_date": "2019-04-16 11:56:20",
      "block": false,
      "translator": "многоголосый закадровый",
      "translator_id": 89,
      "quality": "BDRip"
    },
    {
      "title_ru": "Мисс Пуля",
      "title_en": "Miss Bala",
      "year": 2019,
      "kinopoisk_id": 1100567,
      "type": "movie",
      "iframe_url": "",
      "added_date": "2019-04-16 11:54:32",
      "block": false,
      "translator": "многоголосый закадровый",
      "translator_id": 89,
      "quality": "WEB-DL"
    },
    {
      "title_ru": "Стекло",
      "title_en": "Glass",
      "year": 2019,
      "kinopoisk_id": 1044601,
      "type": "movie",
      "iframe_url": "",
      "added_date": "2019-04-15 22:49:09",
      "block": false,
      "translator": "Дубляж [Лицензия]",
      "translator_id": 107,
      "quality": "BluRay"
    },
    {
      "title_ru": "Лос-Анджелес в огне",
      "title_en": "Kings",
      "year": 2017,
      "kinopoisk_id": 1008739,
      "type": "movie",
      "iframe_url": "",
      "added_date": "2019-04-15 16:46:09",
      "block": false,
      "translator": "Дубляж [Лицензия]",
      "translator_id": 107,
      "quality": "BluRay"
    },
    {
      "title_ru": "Волшебное перо",
      "title_en": "Čertí brko / The Magic Quil",
      "year": 2018,
      "kinopoisk_id": 1060229,
      "type": "movie",
      "iframe_url": "",
      "added_date": "2019-04-15 16:37:01",
      "block": false,
      "translator": "многоголосый закадровый",
      "translator_id": 89,
      "quality": "BDRip"
    },
    {
      "title_ru": "Миррейес против Годинеса",
      "title_en": "Mirreyes contra Godinez (Mirreyes vs. Godinez)",
      "year": 2018,
      "kinopoisk_id": 1076091,
      "type": "movie",
      "iframe_url": "",
      "added_date": "2019-04-15 16:31:55",
      "block": false,
      "translator": "многоголосый закадровый",
      "translator_id": 89,
      "quality": "DVDRip"
    },
    {
      "title_ru": "Великий северный путь",
      "title_en": "",
      "year": 2019,
      "kinopoisk_id": 958530,
      "type": "movie",
      "iframe_url": "",
      "added_date": "2019-04-15 13:18:22",
      "block": [
        "RU"
      ],
      "translator": "Не требуется",
      "translator_id": 92,
      "quality": "WEB-DL"
    },
    {
      "title_ru": "Тим Талер, или Проданный смех",
      "title_en": "Timm Thaler oder das verkaufte Lachen",
      "year": 2017,
      "kinopoisk_id": 904247,
      "type": "movie",
      "iframe_url": "",
      "added_date": "2019-04-15 13:00:41",
      "block": [
        "RU"
      ],
      "translator": "Дубляж [Лицензия]",
      "translator_id": 107,
      "quality": "BluRay"
    },
    {
      "title_ru": "Хеллбой ",
      "title_en": "Hellboy",
      "year": 2019,
      "kinopoisk_id": 693331,
      "type": "movie",
      "iframe_url": "",
      "added_date": "2019-04-14 23:53:51",
      "block": false,
      "translator": "Дубляж",
      "translator_id": 82,
      "quality": "TS"
    },
    {
      "title_ru": "Голодные Z",
      "title_en": "Les affamés",
      "year": 2017,
      "kinopoisk_id": 1029675,
      "type": "movie",
      "iframe_url": "",
      "added_date": "2019-04-14 18:08:32",
      "block": false,
      "translator": "Дубляж [Лицензия]",
      "translator_id": 107,
      "quality": "WEB-DL"
    }
  ]
}
