{
  "items": [
    {
      "title_ru": "Такси 2",
      "title_en": "Taxi 2",
      "year": 2000,
      "kinopoisk_id": 854,
      "type": "movie",
      "iframe_url": "",
      "added_date": "2018-07-30 10:29:48",
      "block": false,
      "translator": "Дубляж [Лицензия]",
      "translator_id": 107,
      "quality": "HDRip"
    },
    {
      "title_ru": "Крик 3",
      "title_en": "Scream 3",
      "year": 2000,
      "kinopoisk_id": 2259,
      "type": "movie",
      "iframe_url": "",
      "added_date": "2018-07-30 10:29:48",
      "block": false,
      "translator": "Дубляж",
      "translator_id": 82,
      "quality": "BluRay"
    },
    {
      "title_ru": "Мужчина по вызову",
      "title_en": "Deuce Bigalow: Male Gigolo",
      "year": 1999,
      "kinopoisk_id": 4198,
      "type": "movie",
      "iframe_url": "",
      "added_date": "2018-07-30 10:29:48",
      "block": false,
      "translator": "одноголосый закадровый",
      "translator_id": 93,
      "quality": "HDRip"
    },
    {
      "title_ru": "Эрин Брокович",
      "title_en": "Erin Brockovich",
      "year": 2000,
      "kinopoisk_id": 661,
      "type": "movie",
      "iframe_url": "",
      "added_date": "2018-07-30 10:29:48",
      "block": false,
      "translator": "Дубляж",
      "translator_id": 82,
      "quality": "HDRip"
    },
    {
      "title_ru": "Ни поездов, ни самолетов…",
      "title_en": "No Trains No Planes",
      "year": 1999,
      "kinopoisk_id": 56594,
      "type": "movie",
      "iframe_url": "",
      "added_date": "2018-07-30 10:29:38",
      "block": false,
      "translator": "двухголосый закадровый",
      "translator_id": 81,
      "quality": "DVDRip"
    },
    {
      "title_ru": "Прах Анджелы",
      "title_en": "Angela's Ashes",
      "year": 1999,
      "kinopoisk_id": 5261,
      "type": "movie",
      "iframe_url": "",
      "added_date": "2018-07-30 10:29:38",
      "block": false,
      "translator": "многоголосый закадровый",
      "translator_id": 89,
      "quality": "HDRip"
    },
    {
      "title_ru": "Послание в бутылке",
      "title_en": "Message in a Bottle",
      "year": 1999,
      "kinopoisk_id": 1656,
      "type": "movie",
      "iframe_url": "",
      "added_date": "2018-07-30 10:29:38",
      "block": false,
      "translator": "Дубляж",
      "translator_id": 82,
      "quality": "HDRip"
    },
    {
      "title_ru": "Анализируй это",
      "title_en": "Analyze This",
      "year": 1999,
      "kinopoisk_id": 1594,
      "type": "movie",
      "iframe_url": "",
      "added_date": "2018-07-30 10:29:38",
      "block": false,
      "translator": "Дубляж",
      "translator_id": 82,
      "quality": "HDRip"
    },
    {
      "title_ru": "Девятые врата",
      "title_en": "The Ninth Gate",
      "year": 1999,
      "kinopoisk_id": 11637,
      "type": "movie",
      "iframe_url": "",
      "added_date": "2018-07-30 10:29:37",
      "block": false,
      "translator": "Дубляж",
      "translator_id": 82,
      "quality": "HDRip"
    },
    {
      "title_ru": "В отрыв!",
      "title_en": "Human Traffic",
      "year": 1999,
      "kinopoisk_id": 51388,
      "type": "movie",
      "iframe_url": "",
      "added_date": "2018-07-30 10:29:37",
      "block": false,
      "translator": "Дубляж",
      "translator_id": 82,
      "quality": "HDRip"
    },
    {
      "title_ru": "Быть Джоном Малковичем",
      "title_en": "Being John Malkovich",
      "year": 1999,
      "kinopoisk_id": 462,
      "type": "movie",
      "iframe_url": "",
      "added_date": "2018-07-30 10:29:37",
      "block": false,
      "translator": "Дубляж",
      "translator_id": 82,
      "quality": "HDRip"
    },
    {
      "title_ru": "Великолепный",
      "title_en": "Boh lei chun",
      "year": 1999,
      "kinopoisk_id": 22803,
      "type": "movie",
      "iframe_url": "",
      "added_date": "2018-07-30 10:29:37",
      "block": false,
      "translator": "одноголосый закадровый",
      "translator_id": 93,
      "quality": "BluRay"
    },
    {
      "title_ru": "Магнолия",
      "title_en": "Magnolia",
      "year": 1999,
      "kinopoisk_id": 477,
      "type": "movie",
      "iframe_url": "",
      "added_date": "2018-07-30 10:29:37",
      "block": false,
      "translator": "многоголосый закадровый",
      "translator_id": 89,
      "quality": "HDRip"
    },
    {
      "title_ru": "Сон в летнюю ночь",
      "title_en": "A Midsummer Night's Dream",
      "year": 1999,
      "kinopoisk_id": 5208,
      "type": "movie",
      "iframe_url": "",
      "added_date": "2018-07-30 10:29:37",
      "block": false,
      "translator": "Дубляж",
      "translator_id": 82,
      "quality": "HDRip"
    },
    {
      "title_ru": "Особо тяжкое преступление",
      "title_en": "Felony",
      "year": 2013,
      "kinopoisk_id": 681679,
      "type": "movie",
      "iframe_url": "",
      "added_date": "2018-07-29 18:05:36",
      "block": false,
      "translator": "многоголосый закадровый",
      "translator_id": 89,
      "quality": "BDRip"
    },
    {
      "title_ru": "Дневной свет",
      "title_en": "Daglicht",
      "year": 2013,
      "kinopoisk_id": 703395,
      "type": "movie",
      "iframe_url": "",
      "added_date": "2018-07-29 17:54:39",
      "block": false,
      "translator": "многоголосый закадровый",
      "translator_id": 89,
      "quality": "BDRip"
    },
    {
      "title_ru": "Экспедиция Коряжки",
      "title_en": "Ekspedisjon Knerten",
      "year": 2017,
      "kinopoisk_id": 1098752,
      "type": "movie",
      "iframe_url": "",
      "added_date": "2018-07-29 16:28:53",
      "block": false,
      "translator": "многоголосый закадровый",
      "translator_id": 89,
      "quality": "WEB-DL"
    },
    {
      "title_ru": "Дыши во мгле",
      "title_en": "Dans la brume",
      "year": 2018,
      "kinopoisk_id": 1027311,
      "type": "movie",
      "iframe_url": "",
      "added_date": "2018-07-29 16:16:49",
      "block": false,
      "translator": "Дубляж",
      "translator_id": 82,
      "quality": "BDRip"
    },
    {
      "title_ru": "Война снайпера",
      "title_en": "",
      "year": 2018,
      "kinopoisk_id": 1115422,
      "type": "movie",
      "iframe_url": "",
      "added_date": "2018-07-29 12:11:10",
      "block": false,
      "translator": "Не требуется",
      "translator_id": 92,
      "quality": "WEB-DL"
    },
    {
      "title_ru": "Суета сует",
      "title_en": "Rabhasa",
      "year": 2014,
      "kinopoisk_id": 851436,
      "type": "movie",
      "iframe_url": "",
      "added_date": "2018-07-29 11:52:21",
      "block": false,
      "translator": "многоголосый закадровый",
      "translator_id": 89,
      "quality": "WEB-DL"
    }
  ]
}
