{
  "items": [
    {
      "title_ru": "Звёздные войны: Скайуокер. Восход",
      "title_en": "Star Wars: Episode IX - The Rise of Skywalker",
      "year": 2019,
      "kinopoisk_id": 718222,
      "type": "movie",
      "iframe_url": "",
      "added_date": "2020-03-31 14:23:01",
      "block": false,
      "translator": "Дубляж [Лицензия]",
      "translator_id": 107,
      "quality": "BDRip"
    },
    {
      "title_ru": "(НЕ)идеальный мужчина",
      "title_en": "",
      "year": 2020,
      "kinopoisk_id": 1162847,
      "type": "movie",
      "iframe_url": "",
      "added_date": "2020-03-31 14:22:02",
      "block": [
        "RU",
        "UA"
      ],
      "translator": "Не требуется",
      "translator_id": 92,
      "quality": "WEBRip"
    },
    {
      "title_ru": "Достать ножи",
      "title_en": "Knives Out",
      "year": 2019,
      "kinopoisk_id": 1188529,
      "type": "movie",
      "iframe_url": "",
      "added_date": "2020-03-31 13:54:01",
      "block": [
        "RU",
        "UA"
      ],
      "translator": "Дубляж [Лицензия]",
      "translator_id": 107,
      "quality": "BDRip"
    },
    {
      "title_ru": "Джуманджи: Новый уровень",
      "title_en": "Jumanji: The Next Level",
      "year": 2019,
      "kinopoisk_id": 1112539,
      "type": "movie",
      "iframe_url": "",
      "added_date": "2020-03-31 13:53:02",
      "block": false,
      "translator": "Дубляж [Лицензия]",
      "translator_id": 107,
      "quality": "BDRip"
    },
    {
      "title_ru": "Холоп",
      "title_en": "",
      "year": 2019,
      "kinopoisk_id": 1183582,
      "type": "movie",
      "iframe_url": "",
      "added_date": "2020-03-31 13:52:01",
      "block": false,
      "translator": "Не требуется",
      "translator_id": 92,
      "quality": "WEBRip"
    },
    {
      "title_ru": "Годзилла 2: Король монстров",
      "title_en": "Godzilla: King of Monsters",
      "year": 2019,
      "kinopoisk_id": 840045,
      "type": "movie",
      "iframe_url": "",
      "added_date": "2020-03-31 13:51:01",
      "block": false,
      "translator": "Дубляж [Лицензия]",
      "translator_id": 107,
      "quality": "BDRip"
    },
    {
      "title_ru": "Заражение",
      "title_en": "Contagion",
      "year": 2011,
      "kinopoisk_id": 501821,
      "type": "movie",
      "iframe_url": "",
      "added_date": "2020-03-31 13:45:01",
      "block": false,
      "translator": "Дубляж [Лицензия]",
      "translator_id": 107,
      "quality": "BDRip"
    },
    {
      "title_ru": "Мстители: Финал",
      "title_en": "Avengers: Endgame",
      "year": 2019,
      "kinopoisk_id": 843650,
      "type": "movie",
      "iframe_url": "",
      "added_date": "2020-03-31 13:36:02",
      "block": false,
      "translator": "Дубляж",
      "translator_id": 82,
      "quality": "BDRip"
    },
    {
      "title_ru": "Калейдоскоп судьбы",
      "title_en": "",
      "year": 2017,
      "kinopoisk_id": 1039243,
      "type": "movie",
      "iframe_url": "",
      "added_date": "2020-03-31 13:15:01",
      "block": false,
      "translator": "Не требуется",
      "translator_id": 92,
      "quality": "HDTV"
    },
    {
      "title_ru": "Влюблён в тебя сотый раз",
      "title_en": "Kimi to 100-kaime no koi",
      "year": 2017,
      "kinopoisk_id": 978687,
      "type": "movie",
      "iframe_url": "",
      "added_date": "2020-03-31 13:14:02",
      "block": false,
      "translator": "двухголосый закадровый",
      "translator_id": 81,
      "quality": "BluRay"
    },
    {
      "title_ru": "Мартин Лютер Кинг: Король без королевства",
      "title_en": "King in the Wilderness",
      "year": 2018,
      "kinopoisk_id": 1115393,
      "type": "movie",
      "iframe_url": "",
      "added_date": "2020-03-31 13:13:01",
      "block": false,
      "translator": "Профессиональный (многоголосый)",
      "translator_id": 126,
      "quality": "BluRay"
    },
    {
      "title_ru": "Наша неполная история",
      "title_en": "Hamari Adhuri Kahani",
      "year": 2015,
      "kinopoisk_id": 821695,
      "type": "movie",
      "iframe_url": "",
      "added_date": "2020-03-31 13:12:01",
      "block": false,
      "translator": "Профессиональный (многоголосый) [Лицензия]",
      "translator_id": 110,
      "quality": "BluRay"
    },
    {
      "title_ru": "Миссис К",
      "title_en": "Mrs K",
      "year": 2016,
      "kinopoisk_id": 1009252,
      "type": "movie",
      "iframe_url": "",
      "added_date": "2020-03-31 13:09:01",
      "block": false,
      "translator": "многоголосый закадровый",
      "translator_id": 89,
      "quality": "DVDRip"
    },
    {
      "title_ru": "Коронный прием",
      "title_en": "Signature Move",
      "year": 2017,
      "kinopoisk_id": 984586,
      "type": "movie",
      "iframe_url": "",
      "added_date": "2020-03-31 13:08:01",
      "block": false,
      "translator": "многоголосый закадровый",
      "translator_id": 89,
      "quality": "WEBRip"
    },
    {
      "title_ru": "WIXOSS: Разрушенный селектор",
      "title_en": "Gekijouban Selector Destructed WIXOSS",
      "year": 2016,
      "kinopoisk_id": 923866,
      "type": "movie",
      "iframe_url": "",
      "added_date": "2020-03-31 13:07:02",
      "block": false,
      "translator": "многоголосый закадровый",
      "translator_id": 89,
      "quality": "HDRip"
    },
    {
      "title_ru": "Утиное масло",
      "title_en": "Duck Butter",
      "year": 2018,
      "kinopoisk_id": 1053939,
      "type": "movie",
      "iframe_url": "",
      "added_date": "2020-03-31 13:06:01",
      "block": false,
      "translator": "многоголосый закадровый",
      "translator_id": 89,
      "quality": "BluRay"
    },
    {
      "title_ru": "Генезис",
      "title_en": "Genesis",
      "year": 2016,
      "kinopoisk_id": 893857,
      "type": "movie",
      "iframe_url": "",
      "added_date": "2020-03-31 13:05:01",
      "block": false,
      "translator": "многоголосый закадровый",
      "translator_id": 89,
      "quality": "BluRay"
    },
    {
      "title_ru": "Отель «Спасение» / Дом спасения",
      "title_en": "Hotel Salvation",
      "year": 2016,
      "kinopoisk_id": 999984,
      "type": "movie",
      "iframe_url": "",
      "added_date": "2020-03-31 13:04:02",
      "block": false,
      "translator": "многоголосый закадровый",
      "translator_id": 89,
      "quality": "BluRay"
    },
    {
      "title_ru": "200 градусов по Фаренгейту",
      "title_en": "200 Degrees",
      "year": 2017,
      "kinopoisk_id": 934810,
      "type": "movie",
      "iframe_url": "",
      "added_date": "2020-03-31 13:03:01",
      "block": false,
      "translator": "многоголосый закадровый",
      "translator_id": 89,
      "quality": "BluRay"
    },
    {
      "title_ru": "Калифорния",
      "title_en": "Fishbowl California",
      "year": 2018,
      "kinopoisk_id": 998861,
      "type": "movie",
      "iframe_url": "",
      "added_date": "2020-03-31 13:02:01",
      "block": false,
      "translator": "многоголосый закадровый",
      "translator_id": 89,
      "quality": "BluRay"
    }
  ]
}
